{
  "context": {
    "game_pk": 716846,
    "date": {
      "year": 2023,
      "month": 8,
      "day": 26
    },
    "venue_name": "Rogers Centre",
    "weather": {
      "condition": "Roof Closed",
      "temperature": 68,
      "wind_speed": 0
    },
    "home_team": {
      "id": 141,
      "players": [
        {
          "name": "Brandon Belt",
          "position": "DesignatedHitter"
        },
        {
          "name": "George Springer",
          "position": "RightField"
        },
        {
          "name": "Hyun Jin Ryu",
          "position": "Pitcher"
        },
        {
          "name": "Yimi García",
          "position": "Pitcher"
        },
        {
          "name": "Kevin Gausman",
          "position": "Pitcher"
        },
        {
          "name": "Whit Merrifield",
          "position": "LeftField"
        },
        {
          "name": "Kevin Kiermaier",
          "position": "CenterField"
        },
        {
          "name": "Chris Bassitt",
          "position": "Pitcher"
        },
        {
          "name": "Jordan Romano",
          "position": "Pitcher"
        },
        {
          "name": "José Berríos",
          "position": "Pitcher"
        },
        {
          "name": "Cavan Biggio",
          "position": "SecondBase"
        },
        {
          "name": "Tim Mayza",
          "position": "Pitcher"
        },
        {
          "name": "Danny Jansen",
          "position": "Catcher"
        },
        {
          "name": "Génesis Cabrera",
          "position": "Pitcher"
        },
        {
          "name": "Matt Chapman",
          "position": "ThirdBase"
        },
        {
          "name": "Erik Swanson",
          "position": "Pitcher"
        },
        {
          "name": "Daulton Varsho",
          "position": "CenterField"
        },
        {
          "name": "Jordan Hicks",
          "position": "Pitcher"
        },
        {
          "name": "Vladimir Guerrero Jr.",
          "position": "FirstBase"
        },
        {
          "name": "Bo Bichette",
          "position": "DesignatedHitter"
        },
        {
          "name": "Santiago Espinal",
          "position": "Shortstop"
        },
        {
          "name": "Bowden Francis",
          "position": "Pitcher"
        },
        {
          "name": "Trevor Richards",
          "position": "Pitcher"
        },
        {
          "name": "Alejandro Kirk",
          "position": "Catcher"
        },
        {
          "name": "Davis Schneider",
          "position": "SecondBase"
        }
      ]
    },
    "away_team": {
      "id": 114,
      "players": [
        {
          "name": "Noah Syndergaard",
          "position": "Pitcher"
        },
        {
          "name": "Kole Calhoun",
          "position": "FirstBase"
        },
        {
          "name": "Cam Gallagher",
          "position": "Catcher"
        },
        {
          "name": "Eric Haase",
          "position": "Catcher"
        },
        {
          "name": "José Ramírez",
          "position": "DesignatedHitter"
        },
        {
          "name": "Sam Hentges",
          "position": "Pitcher"
        },
        {
          "name": "Ramón Laureano",
          "position": "RightField"
        },
        {
          "name": "Oscar Gonzalez",
          "position": "LeftField"
        },
        {
          "name": "Enyel De Los Santos",
          "position": "Pitcher"
        },
        {
          "name": "Emmanuel Clase",
          "position": "Pitcher"
        },
        {
          "name": "Cody Morris",
          "position": "Pitcher"
        },
        {
          "name": "Trevor Stephan",
          "position": "Pitcher"
        },
        {
          "name": "Myles Straw",
          "position": "CenterField"
        },
        {
          "name": "Andrés Giménez",
          "position": "SecondBase"
        },
        {
          "name": "Bo Naylor",
          "position": "Catcher"
        },
        {
          "name": "Gavin Williams",
          "position": "Pitcher"
        },
        {
          "name": "Eli Morgan",
          "position": "Pitcher"
        },
        {
          "name": "Logan Allen",
          "position": "Pitcher"
        },
        {
          "name": "Tyler Freeman",
          "position": "ThirdBase"
        },
        {
          "name": "Gabriel Arias",
          "position": "Shortstop"
        },
        {
          "name": "Xzavion Curry",
          "position": "Pitcher"
        },
        {
          "name": "James Karinchak",
          "position": "Pitcher"
        },
        {
          "name": "Tanner Bibee",
          "position": "Pitcher"
        },
        {
          "name": "Nick Sandlin",
          "position": "Pitcher"
        },
        {
          "name": "Steven Kwan",
          "position": "LeftField"
        },
        {
          "name": "Will Brennan",
          "position": "RightField"
        }
      ]
    }
  },
  "plays": [
    {
      "Groundout": {
        "batter": "Kole Calhoun",
        "pitcher": "Hyun Jin Ryu",
        "fielders": [
          "Hyun Jin Ryu"
        ],
        "movements": [
          {
            "runner": "Kole Calhoun",
            "start_base": null,
            "end_base": null,
            "is_out": true
          }
        ]
      }
    },
    {
      "HomeRun": {
        "batter": "José Ramírez",
        "pitcher": "Hyun Jin Ryu",
        "movements": [
          {
            "runner": "José Ramírez",
            "start_base": null,
            "end_base": 4,
            "is_out": false
          }
        ]
      }
    },
    {
      "Strikeout": {
        "batter": "Oscar Gonzalez",
        "pitcher": "Hyun Jin Ryu",
        "movements": [
          {
            "runner": "Oscar Gonzalez",
            "start_base": null,
            "end_base": null,
            "is_out": true
          }
        ]
      }
    },
    {
      "Flyout": {
        "batter": "Ramón Laureano",
        "pitcher": "Hyun Jin Ryu",
        "fielders": [
          "Davis Schneider"
        ],
        "movements": [
          {
            "runner": "Ramón Laureano",
            "start_base": null,
            "end_base": null,
            "is_out": true
          }
        ]
      }
    },
    {
      "Double": {
        "batter": "Whit Merrifield",
        "pitcher": "Logan Allen",
        "movements": [
          {
            "runner": "Whit Merrifield",
            "start_base": null,
            "end_base": 2,
            "is_out": false
          }
        ]
      }
    },
    {
      "Single": {
        "batter": "Bo Bichette",
        "pitcher": "Logan Allen",
        "movements": [
          {
            "runner": "Bo Bichette",
            "start_base": null,
            "end_base": 1,
            "is_out": false
          },
          {
            "runner": "Whit Merrifield",
            "start_base": 2,
            "end_base": 4,
            "is_out": false
          }
        ]
      }
    },
    {
      "Forceout": {
        "batter": "Vladimir Guerrero Jr.",
        "pitcher": "Logan Allen",
        "fielders": [
          "Andrés Giménez"
        ],
        "movements": [
          {
            "runner": "Bo Bichette",
            "start_base": 1,
            "end_base": null,
            "is_out": true
          },
          {
            "runner": "Vladimir Guerrero Jr.",
            "start_base": null,
            "end_base": 1,
            "is_out": false
          }
        ]
      }
    },
    {
      "Forceout": {
        "batter": "George Springer",
        "pitcher": "Logan Allen",
        "fielders": [
          "Tyler Freeman"
        ],
        "movements": [
          {
            "runner": "Vladimir Guerrero Jr.",
            "start_base": 1,
            "end_base": null,
            "is_out": true
          },
          {
            "runner": "George Springer",
            "start_base": null,
            "end_base": 1,
            "is_out": false
          }
        ]
      }
    },
    {
      "HomeRun": {
        "batter": "Davis Schneider",
        "pitcher": "Logan Allen",
        "movements": [
          {
            "runner": "Davis Schneider",
            "start_base": null,
            "end_base": 4,
            "is_out": false
          },
          {
            "runner": "George Springer",
            "start_base": 1,
            "end_base": 4,
            "is_out": false
          }
        ]
      }
    },
    {
      "Flyout": {
        "batter": "Danny Jansen",
        "pitcher": "Logan Allen",
        "fielders": [
          "Myles Straw"
        ],
        "movements": [
          {
            "runner": "Danny Jansen",
            "start_base": null,
            "end_base": null,
            "is_out": true
          }
        ]
      }
    },
    {
      "Strikeout": {
        "batter": "Andrés Giménez",
        "pitcher": "Hyun Jin Ryu",
        "movements": [
          {
            "runner": "Andrés Giménez",
            "start_base": null,
            "end_base": null,
            "is_out": true
          }
        ]
      }
    },
    {
      "Strikeout": {
        "batter": "Gabriel Arias",
        "pitcher": "Hyun Jin Ryu",
        "movements": [
          {
            "runner": "Gabriel Arias",
            "start_base": null,
            "end_base": null,
            "is_out": true
          }
        ]
      }
    },
    {
      "Groundout": {
        "batter": "Tyler Freeman",
        "pitcher": "Hyun Jin Ryu",
        "fielders": [
          "Hyun Jin Ryu"
        ],
        "movements": [
          {
            "runner": "Tyler Freeman",
            "start_base": null,
            "end_base": null,
            "is_out": true
          }
        ]
      }
    },
    {
      "Walk": {
        "batter": "Matt Chapman",
        "pitcher": "Logan Allen",
        "movements": [
          {
            "runner": "Matt Chapman",
            "start_base": null,
            "end_base": 1,
            "is_out": false
          }
        ]
      }
    },
    {
      "Flyout": {
        "batter": "Santiago Espinal",
        "pitcher": "Logan Allen",
        "fielders": [
          "Myles Straw"
        ],
        "movements": [
          {
            "runner": "Santiago Espinal",
            "start_base": null,
            "end_base": null,
            "is_out": true
          }
        ]
      }
    },
    {
      "Flyout": {
        "batter": "Daulton Varsho",
        "pitcher": "Logan Allen",
        "fielders": [
          "Oscar Gonzalez"
        ],
        "movements": [
          {
            "runner": "Daulton Varsho",
            "start_base": null,
            "end_base": null,
            "is_out": true
          }
        ]
      }
    },
    {
      "Strikeout": {
        "batter": "Whit Merrifield",
        "pitcher": "Logan Allen",
        "movements": [
          {
            "runner": "Whit Merrifield",
            "start_base": null,
            "end_base": null,
            "is_out": true
          }
        ]
      }
    },
    {
      "Double": {
        "batter": "Cam Gallagher",
        "pitcher": "Hyun Jin Ryu",
        "movements": [
          {
            "runner": "Cam Gallagher",
            "start_base": null,
            "end_base": 2,
            "is_out": false
          }
        ]
      }
    },
    {
      "SacBunt": {
        "batter": "Myles Straw",
        "pitcher": "Hyun Jin Ryu",
        "fielders": [
          "Matt Chapman"
        ],
        "runner": "Cam Gallagher",
        "movements": [
          {
            "runner": "Myles Straw",
            "start_base": null,
            "end_base": null,
            "is_out": true
          },
          {
            "runner": "Cam Gallagher",
            "start_base": 2,
            "end_base": 3,
            "is_out": false
          }
        ]
      }
    },
    {
      "Flyout": {
        "batter": "Kole Calhoun",
        "pitcher": "Hyun Jin Ryu",
        "fielders": [
          "Whit Merrifield"
        ],
        "movements": [
          {
            "runner": "Kole Calhoun",
            "start_base": null,
            "end_base": null,
            "is_out": true
          }
        ]
      }
    },
    {
      "Lineout": {
        "batter": "José Ramírez",
        "pitcher": "Hyun Jin Ryu",
        "fielders": [
          "Daulton Varsho"
        ],
        "movements": [
          {
            "runner": "José Ramírez",
            "start_base": null,
            "end_base": null,
            "is_out": true
          }
        ]
      }
    },
    {
      "Lineout": {
        "batter": "Bo Bichette",
        "pitcher": "Logan Allen",
        "fielders": [
          "Andrés Giménez"
        ],
        "movements": [
          {
            "runner": "Bo Bichette",
            "start_base": null,
            "end_base": null,
            "is_out": true
          }
        ]
      }
    },
    {
      "Flyout": {
        "batter": "Vladimir Guerrero Jr.",
        "pitcher": "Logan Allen",
        "fielders": [
          "Myles Straw"
        ],
        "movements": [
          {
            "runner": "Vladimir Guerrero Jr.",
            "start_base": null,
            "end_base": null,
            "is_out": true
          }
        ]
      }
    },
    {
      "Strikeout": {
        "batter": "George Springer",
        "pitcher": "Logan Allen",
        "movements": [
          {
            "runner": "George Springer",
            "start_base": null,
            "end_base": null,
            "is_out": true
          }
        ]
      }
    },
    {
      "Groundout": {
        "batter": "Oscar Gonzalez",
        "pitcher": "Hyun Jin Ryu",
        "fielders": [
          "Matt Chapman"
        ],
        "movements": [
          {
            "runner": "Oscar Gonzalez",
            "start_base": null,
            "end_base": null,
            "is_out": true
          }
        ]
      }
    },
    {
      "Flyout": {
        "batter": "Ramón Laureano",
        "pitcher": "Hyun Jin Ryu",
        "fielders": [
          "Daulton Varsho"
        ],
        "movements": [
          {
            "runner": "Ramón Laureano",
            "start_base": null,
            "end_base": null,
            "is_out": true
          }
        ]
      }
    },
    {
      "Strikeout": {
        "batter": "Andrés Giménez",
        "pitcher": "Hyun Jin Ryu",
        "movements": [
          {
            "runner": "Andrés Giménez",
            "start_base": null,
            "end_base": null,
            "is_out": true
          }
        ]
      }
    },
    {
      "Double": {
        "batter": "Davis Schneider",
        "pitcher": "Logan Allen",
        "movements": [
          {
            "runner": "Davis Schneider",
            "start_base": null,
            "end_base": 2,
            "is_out": false
          }
        ]
      }
    },
    {
      "Single": {
        "batter": "Danny Jansen",
        "pitcher": "Logan Allen",
        "movements": [
          {
            "runner": "Danny Jansen",
            "start_base": null,
            "end_base": 1,
            "is_out": false
          },
          {
            "runner": "Danny Jansen",
            "start_base": 1,
            "end_base": 2,
            "is_out": false
          },
          {
            "runner": "Davis Schneider",
            "start_base": 2,
            "end_base": 3,
            "is_out": false
          }
        ]
      }
    },
    {
      "Single": {
        "batter": "Matt Chapman",
        "pitcher": "Logan Allen",
        "movements": [
          {
            "runner": "Matt Chapman",
            "start_base": null,
            "end_base": 1,
            "is_out": false
          },
          {
            "runner": "Davis Schneider",
            "start_base": 3,
            "end_base": 4,
            "is_out": false
          },
          {
            "runner": "Danny Jansen",
            "start_base": 2,
            "end_base": 3,
            "is_out": false
          }
        ]
      }
    },
    {
      "SacFly": {
        "batter": "Santiago Espinal",
        "pitcher": "Logan Allen",
        "fielders": [
          "Myles Straw"
        ],
        "scoring_runner": "Danny Jansen",
        "movements": [
          {
            "runner": "Santiago Espinal",
            "start_base": null,
            "end_base": null,
            "is_out": true
          },
          {
            "runner": "Danny Jansen",
            "start_base": 3,
            "end_base": 4,
            "is_out": false
          }
        ]
      }
    },
    {
      "Flyout": {
        "batter": "Daulton Varsho",
        "pitcher": "Logan Allen",
        "fielders": [
          "Myles Straw"
        ],
        "movements": [
          {
            "runner": "Daulton Varsho",
            "start_base": null,
            "end_base": null,
            "is_out": true
          }
        ]
      }
    },
    {
      "Flyout": {
        "batter": "Whit Merrifield",
        "pitcher": "Logan Allen",
        "fielders": [
          "Oscar Gonzalez"
        ],
        "movements": [
          {
            "runner": "Whit Merrifield",
            "start_base": null,
            "end_base": null,
            "is_out": true
          }
        ]
      }
    },
    {
      "Strikeout": {
        "batter": "Gabriel Arias",
        "pitcher": "Hyun Jin Ryu",
        "movements": [
          {
            "runner": "Gabriel Arias",
            "start_base": null,
            "end_base": null,
            "is_out": true
          }
        ]
      }
    },
    {
      "HomeRun": {
        "batter": "Tyler Freeman",
        "pitcher": "Hyun Jin Ryu",
        "movements": [
          {
            "runner": "Tyler Freeman",
            "start_base": null,
            "end_base": 4,
            "is_out": false
          }
        ]
      }
    },
    {
      "Groundout": {
        "batter": "Cam Gallagher",
        "pitcher": "Hyun Jin Ryu",
        "fielders": [
          "Santiago Espinal"
        ],
        "movements": [
          {
            "runner": "Cam Gallagher",
            "start_base": null,
            "end_base": null,
            "is_out": true
          }
        ]
      }
    },
    {
      "Groundout": {
        "batter": "Myles Straw",
        "pitcher": "Hyun Jin Ryu",
        "fielders": [
          "Hyun Jin Ryu"
        ],
        "movements": [
          {
            "runner": "Myles Straw",
            "start_base": null,
            "end_base": null,
            "is_out": true
          }
        ]
      }
    },
    {
      "Double": {
        "batter": "Bo Bichette",
        "pitcher": "Cody Morris",
        "movements": [
          {
            "runner": "Bo Bichette",
            "start_base": null,
            "end_base": 2,
            "is_out": false
          }
        ]
      }
    },
    {
      "PopOut": {
        "batter": "Vladimir Guerrero Jr.",
        "pitcher": "Cody Morris",
        "fielders": [
          "Andrés Giménez"
        ],
        "movements": [
          {
            "runner": "Vladimir Guerrero Jr.",
            "start_base": null,
            "end_base": null,
            "is_out": true
          }
        ]
      }
    },
    {
      "FieldersChoiceOut": {
        "batter": "George Springer",
        "pitcher": "Cody Morris",
        "fielders": [
          "Gabriel Arias"
        ],
        "scoring_runner": "George Springer",
        "movements": [
          {
            "runner": "Bo Bichette",
            "start_base": 2,
            "end_base": null,
            "is_out": true
          },
          {
            "runner": "George Springer",
            "start_base": null,
            "end_base": 1,
            "is_out": false
          }
        ]
      }
    },
    {
      "Walk": {
        "batter": "Davis Schneider",
        "pitcher": "Cody Morris",
        "movements": [
          {
            "runner": "George Springer",
            "start_base": 1,
            "end_base": 2,
            "is_out": false
          },
          {
            "runner": "Davis Schneider",
            "start_base": null,
            "end_base": 1,
            "is_out": false
          }
        ]
      }
    },
    {
      "Strikeout": {
        "batter": "Danny Jansen",
        "pitcher": "Cody Morris",
        "movements": [
          {
            "runner": "Danny Jansen",
            "start_base": null,
            "end_base": null,
            "is_out": true
          }
        ]
      }
    },
    {
      "Single": {
        "batter": "Kole Calhoun",
        "pitcher": "Hyun Jin Ryu",
        "movements": [
          {
            "runner": "Kole Calhoun",
            "start_base": null,
            "end_base": 1,
            "is_out": false
          }
        ]
      }
    },
    {
      "FieldError": {
        "batter": "José Ramírez",
        "pitcher": "Hyun Jin Ryu",
        "fielders": [
          "Matt Chapman"
        ],
        "movements": [
          {
            "runner": "José Ramírez",
            "start_base": null,
            "end_base": 1,
            "is_out": false
          },
          {
            "runner": "Kole Calhoun",
            "start_base": 1,
            "end_base": 2,
            "is_out": false
          }
        ]
      }
    },
    {
      "FieldError": {
        "batter": "Oscar Gonzalez",
        "pitcher": "Hyun Jin Ryu",
        "fielders": [
          "Santiago Espinal"
        ],
        "movements": [
          {
            "runner": "Oscar Gonzalez",
            "start_base": null,
            "end_base": 1,
            "is_out": false
          },
          {
            "runner": "Kole Calhoun",
            "start_base": 2,
            "end_base": 3,
            "is_out": false
          },
          {
            "runner": "José Ramírez",
            "start_base": 1,
            "end_base": 2,
            "is_out": false
          }
        ]
      }
    },
    {
      "HitByPitch": {
        "batter": "Ramón Laureano",
        "pitcher": "Yimi García",
        "movements": [
          {
            "runner": "Kole Calhoun",
            "start_base": 3,
            "end_base": 4,
            "is_out": false
          },
          {
            "runner": "José Ramírez",
            "start_base": 2,
            "end_base": 3,
            "is_out": false
          },
          {
            "runner": "Oscar Gonzalez",
            "start_base": 1,
            "end_base": 2,
            "is_out": false
          },
          {
            "runner": "Ramón Laureano",
            "start_base": null,
            "end_base": 1,
            "is_out": false
          }
        ]
      }
    },
    {
      "Strikeout": {
        "batter": "Andrés Giménez",
        "pitcher": "Yimi García",
        "movements": [
          {
            "runner": "Andrés Giménez",
            "start_base": null,
            "end_base": null,
            "is_out": true
          }
        ]
      }
    },
    {
      "Strikeout": {
        "batter": "Gabriel Arias",
        "pitcher": "Yimi García",
        "movements": [
          {
            "runner": "Gabriel Arias",
            "start_base": null,
            "end_base": null,
            "is_out": true
          }
        ]
      }
    },
    {
      "Strikeout": {
        "batter": "Tyler Freeman",
        "pitcher": "Yimi García",
        "movements": [
          {
            "runner": "Tyler Freeman",
            "start_base": null,
            "end_base": null,
            "is_out": true
          }
        ]
      }
    },
    {
      "Strikeout": {
        "batter": "Matt Chapman",
        "pitcher": "Cody Morris",
        "movements": [
          {
            "runner": "Matt Chapman",
            "start_base": null,
            "end_base": null,
            "is_out": true
          }
        ]
      }
    },
    {
      "Groundout": {
        "batter": "Santiago Espinal",
        "pitcher": "Cody Morris",
        "fielders": [
          "Tyler Freeman"
        ],
        "movements": [
          {
            "runner": "Santiago Espinal",
            "start_base": null,
            "end_base": null,
            "is_out": true
          }
        ]
      }
    },
    {
      "Walk": {
        "batter": "Daulton Varsho",
        "pitcher": "Cody Morris",
        "movements": [
          {
            "runner": "Daulton Varsho",
            "start_base": null,
            "end_base": 1,
            "is_out": false
          }
        ]
      }
    },
    {
      "Walk": {
        "batter": "Whit Merrifield",
        "pitcher": "Cody Morris",
        "movements": [
          {
            "runner": "Daulton Varsho",
            "start_base": 1,
            "end_base": 2,
            "is_out": false
          },
          {
            "runner": "Whit Merrifield",
            "start_base": null,
            "end_base": 1,
            "is_out": false
          }
        ]
      }
    },
    {
      "Strikeout": {
        "batter": "Bo Bichette",
        "pitcher": "Cody Morris",
        "movements": [
          {
            "runner": "Bo Bichette",
            "start_base": null,
            "end_base": null,
            "is_out": true
          }
        ]
      }
    },
    {
      "Groundout": {
        "batter": "Bo Naylor",
        "pitcher": "Erik Swanson",
        "fielders": [
          "Vladimir Guerrero Jr."
        ],
        "movements": [
          {
            "runner": "Bo Naylor",
            "start_base": null,
            "end_base": null,
            "is_out": true
          }
        ]
      }
    },
    {
      "Single": {
        "batter": "Myles Straw",
        "pitcher": "Erik Swanson",
        "movements": [
          {
            "runner": "Myles Straw",
            "start_base": null,
            "end_base": 1,
            "is_out": false
          }
        ]
      }
    },
    {
      "GroundedIntoDoublePlay": {
        "batter": "Kole Calhoun",
        "pitcher": "Tim Mayza",
        "fielders": [
          "Santiago Espinal",
          "Santiago Espinal"
        ],
        "movements": [
          {
            "runner": "Myles Straw",
            "start_base": 1,
            "end_base": null,
            "is_out": true
          },
          {
            "runner": "Kole Calhoun",
            "start_base": null,
            "end_base": null,
            "is_out": true
          }
        ]
      }
    },
    {
      "Single": {
        "batter": "Vladimir Guerrero Jr.",
        "pitcher": "Cody Morris",
        "movements": [
          {
            "runner": "Vladimir Guerrero Jr.",
            "start_base": null,
            "end_base": 1,
            "is_out": false
          }
        ]
      }
    },
    {
      "Double": {
        "batter": "George Springer",
        "pitcher": "Cody Morris",
        "movements": [
          {
            "runner": "George Springer",
            "start_base": null,
            "end_base": 2,
            "is_out": false
          },
          {
            "runner": "Vladimir Guerrero Jr.",
            "start_base": 1,
            "end_base": 3,
            "is_out": false
          }
        ]
      }
    },
    {
      "Single": {
        "batter": "Davis Schneider",
        "pitcher": "James Karinchak",
        "movements": [
          {
            "runner": "Davis Schneider",
            "start_base": null,
            "end_base": 1,
            "is_out": false
          },
          {
            "runner": "Vladimir Guerrero Jr.",
            "start_base": 3,
            "end_base": 4,
            "is_out": false
          },
          {
            "runner": "George Springer",
            "start_base": 2,
            "end_base": 3,
            "is_out": false
          }
        ]
      }
    },
    {
      "HitByPitch": {
        "batter": "Danny Jansen",
        "pitcher": "James Karinchak",
        "movements": [
          {
            "runner": "Davis Schneider",
            "start_base": 1,
            "end_base": 2,
            "is_out": false
          },
          {
            "runner": "Danny Jansen",
            "start_base": null,
            "end_base": 1,
            "is_out": false
          }
        ]
      }
    },
    {
      "PopOut": {
        "batter": "Matt Chapman",
        "pitcher": "James Karinchak",
        "fielders": [
          "Kole Calhoun"
        ],
        "movements": [
          {
            "runner": "Matt Chapman",
            "start_base": null,
            "end_base": null,
            "is_out": true
          }
        ]
      }
    },
    {
      "Strikeout": {
        "batter": "Santiago Espinal",
        "pitcher": "James Karinchak",
        "movements": [
          {
            "runner": "Santiago Espinal",
            "start_base": null,
            "end_base": null,
            "is_out": true
          }
        ]
      }
    },
    {
      "Single": {
        "batter": "Daulton Varsho",
        "pitcher": "James Karinchak",
        "movements": [
          {
            "runner": "Daulton Varsho",
            "start_base": null,
            "end_base": 1,
            "is_out": false
          },
          {
            "runner": "Davis Schneider",
            "start_base": 2,
            "end_base": 3,
            "is_out": false
          },
          {
            "runner": "Davis Schneider",
            "start_base": 3,
            "end_base": 4,
            "is_out": false
          },
          {
            "runner": "Danny Jansen",
            "start_base": 1,
            "end_base": 2,
            "is_out": false
          },
          {
            "runner": "Danny Jansen",
            "start_base": 2,
            "end_base": 3,
            "is_out": false
          },
          {
            "runner": "George Springer",
            "start_base": 3,
            "end_base": 4,
            "is_out": false
          }
        ]
      }
    },
    {
      "CaughtStealing": {
        "base": 2,
        "runner": "Daulton Varsho",
        "fielders": [
          "Bo Naylor"
        ],
        "movements": [
          {
            "runner": "Daulton Varsho",
            "start_base": 1,
            "end_base": null,
            "is_out": true
          }
        ]
      }
    },
    {
      "Strikeout": {
        "batter": "José Ramírez",
        "pitcher": "Trevor Richards",
        "movements": [
          {
            "runner": "José Ramírez",
            "start_base": null,
            "end_base": null,
            "is_out": true
          }
        ]
      }
    },
    {
      "Strikeout": {
        "batter": "Oscar Gonzalez",
        "pitcher": "Trevor Richards",
        "movements": [
          {
            "runner": "Oscar Gonzalez",
            "start_base": null,
            "end_base": null,
            "is_out": true
          }
        ]
      }
    },
    {
      "Flyout": {
        "batter": "Ramón Laureano",
        "pitcher": "Trevor Richards",
        "fielders": [
          "Daulton Varsho"
        ],
        "movements": [
          {
            "runner": "Ramón Laureano",
            "start_base": null,
            "end_base": null,
            "is_out": true
          }
        ]
      }
    },
    {
      "Lineout": {
        "batter": "Whit Merrifield",
        "pitcher": "Eli Morgan",
        "fielders": [
          "Myles Straw"
        ],
        "movements": [
          {
            "runner": "Whit Merrifield",
            "start_base": null,
            "end_base": null,
            "is_out": true
          }
        ]
      }
    },
    {
      "Flyout": {
        "batter": "Bo Bichette",
        "pitcher": "Eli Morgan",
        "fielders": [
          "Gabriel Arias"
        ],
        "movements": [
          {
            "runner": "Bo Bichette",
            "start_base": null,
            "end_base": null,
            "is_out": true
          }
        ]
      }
    },
    {
      "Groundout": {
        "batter": "Vladimir Guerrero Jr.",
        "pitcher": "Eli Morgan",
        "fielders": [
          "Kole Calhoun"
        ],
        "movements": [
          {
            "runner": "Vladimir Guerrero Jr.",
            "start_base": null,
            "end_base": null,
            "is_out": true
          }
        ]
      }
    },
    {
      "Flyout": {
        "batter": "Andrés Giménez",
        "pitcher": "Trevor Richards",
        "fielders": [
          "Daulton Varsho"
        ],
        "movements": [
          {
            "runner": "Andrés Giménez",
            "start_base": null,
            "end_base": null,
            "is_out": true
          }
        ]
      }
    },
    {
      "Lineout": {
        "batter": "Gabriel Arias",
        "pitcher": "Trevor Richards",
        "fielders": [
          "Davis Schneider"
        ],
        "movements": [
          {
            "runner": "Gabriel Arias",
            "start_base": null,
            "end_base": null,
            "is_out": true
          }
        ]
      }
    },
    {
      "Flyout": {
        "batter": "Tyler Freeman",
        "pitcher": "Trevor Richards",
        "fielders": [
          "George Springer"
        ],
        "movements": [
          {
            "runner": "Tyler Freeman",
            "start_base": null,
            "end_base": null,
            "is_out": true
          }
        ]
      }
    }
  ]
}